setup.py
nd_probability/Binomialdistribution.py
nd_probability/Gaussiandistribution.py
nd_probability/Generaldistribution.py
nd_probability/__init__.py
nd_probability.egg-info/PKG-INFO
nd_probability.egg-info/SOURCES.txt
nd_probability.egg-info/dependency_links.txt
nd_probability.egg-info/not-zip-safe
nd_probability.egg-info/top_level.txt