Metadata-Version: 1.0
Name: nd-probability
Version: 0.1
Summary: Gaussian and Binomial distributions
Home-page: UNKNOWN
Author: Nachiket Dixit
Author-email: nachiket.dixit@gmail.com
License: UNKNOWN
Platform: UNKNOWN
